functioneer/__init__.py
functioneer/analysis.py
functioneer/parameter.py
functioneer/steps.py
functioneer/util.py
functioneer-0.5.0.dist-info/licenses/LICENSE
functioneer-0.5.0.dist-info/METADATA
functioneer-0.5.0.dist-info/WHEEL
functioneer-0.5.0.dist-info/top_level.txt
functioneer-0.5.0.dist-info/RECORD
