Metadata-Version: 2.4
Name: functioneer
Version: 0.5.0
Summary: Effortlessly explore function behavior with the ultimate batch runner.
Author-email: Quinn Marsh <quinnmarsh@hotmail.com>
Maintainer-email: Quinn Marsh <quinnmarsh@hotmail.com>
License: MIT
Project-URL: Homepage, https://github.com/qthedoc/functioneer
Project-URL: Issues, https://github.com/qthedoc/functioneer/issues
Project-URL: Funding, https://donate.pypi.org
Project-URL: Say Thanks!, http://quinnmarsh.com
Keywords: functioneer,analysis,batch run,batch runner,automation,autorun,trade space,digital twin
Classifier: Development Status :: 4 - Beta
Classifier: Intended Audience :: Science/Research
Classifier: Topic :: Scientific/Engineering
Classifier: License :: OSI Approved :: MIT License
Classifier: Programming Language :: Python :: 3.7
Classifier: Programming Language :: Python :: 3.8
Classifier: Programming Language :: Python :: 3.9
Classifier: Programming Language :: Python :: 3.10
Classifier: Programming Language :: Python :: 3.11
Classifier: Programming Language :: Python :: 3.12
Classifier: Programming Language :: Python :: 3.13
Requires-Python: >=3.7
License-File: LICENSE
Requires-Dist: numpy>=1.18.5
Requires-Dist: scipy>=1.5.2
Requires-Dist: pandas>=1.0.5
Dynamic: license-file
